django_timezone-0.2.dist-info/DESCRIPTION.rst
django_timezone-0.2.dist-info/METADATA
django_timezone-0.2.dist-info/RECORD
django_timezone-0.2.dist-info/WHEEL
django_timezone-0.2.dist-info/metadata.json
django_timezone-0.2.dist-info/top_level.txt
timezone/__init__.py
timezone/timezone.py
timezone/tests/__init__.py
timezone/tests/settings.py
timezone/tests/tests.py
